exact_sync/__init__.py
exact_sync/exact_enums.py
exact_sync/exact_errors.py
exact_sync/exact_manager.py
exact_sync/v1/__init__.py
exact_sync/v1/api_client.py
exact_sync/v1/configuration.py
exact_sync/v1/rest.py
exact_sync/v1/api/__init__.py
exact_sync/v1/api/annotation_media_files_api.py
exact_sync/v1/api/annotation_types_api.py
exact_sync/v1/api/annotations_api.py
exact_sync/v1/api/image_registration_api.py
exact_sync/v1/api/image_sets_api.py
exact_sync/v1/api/images_api.py
exact_sync/v1/api/log_image_actions_api.py
exact_sync/v1/api/pagination_base_api.py
exact_sync/v1/api/processing_api.py
exact_sync/v1/api/products_api.py
exact_sync/v1/api/screening_modes_api.py
exact_sync/v1/api/set_tags_api.py
exact_sync/v1/api/team_membership_api.py
exact_sync/v1/api/teams_api.py
exact_sync/v1/api/users_api.py
exact_sync/v1/api/verifications_api.py
exact_sync/v1/models/__init__.py
exact_sync/v1/models/annotation.py
exact_sync/v1/models/annotation_media_file.py
exact_sync/v1/models/annotation_media_files.py
exact_sync/v1/models/annotation_type.py
exact_sync/v1/models/annotation_types.py
exact_sync/v1/models/annotations.py
exact_sync/v1/models/image.py
exact_sync/v1/models/image_registration.py
exact_sync/v1/models/image_registrations.py
exact_sync/v1/models/image_set.py
exact_sync/v1/models/image_sets.py
exact_sync/v1/models/images.py
exact_sync/v1/models/log_image_action.py
exact_sync/v1/models/log_image_actions.py
exact_sync/v1/models/plugin.py
exact_sync/v1/models/plugin_job.py
exact_sync/v1/models/plugin_jobs.py
exact_sync/v1/models/plugin_result.py
exact_sync/v1/models/plugin_result_annotation.py
exact_sync/v1/models/plugin_result_annotations.py
exact_sync/v1/models/plugin_result_bitmap.py
exact_sync/v1/models/plugin_result_bitmaps.py
exact_sync/v1/models/plugin_result_entries.py
exact_sync/v1/models/plugin_result_entry.py
exact_sync/v1/models/plugin_results.py
exact_sync/v1/models/plugins.py
exact_sync/v1/models/product.py
exact_sync/v1/models/products.py
EXCAT_Sync-0.0.38.dist-info/LICENSE
EXCAT_Sync-0.0.38.dist-info/METADATA
EXCAT_Sync-0.0.38.dist-info/WHEEL
EXCAT_Sync-0.0.38.dist-info/top_level.txt
EXCAT_Sync-0.0.38.dist-info/RECORD
