Metadata-Version: 2.1
Name: EXCAT-Sync
Version: 0.0.38
Summary: A package to download images and annotations from the EXACT Server https://github.com/ChristianMarzahl/Exact
Home-page: https://github.com/ChristianMarzahl/EXACT-Sync
Author: Christian Marzahl
Author-email: christian.marzahl@gamil.com
Classifier: Programming Language :: Python :: 3
Classifier: License :: OSI Approved :: MIT License
Classifier: Operating System :: OS Independent
Requires-Python: >=3.6
License-File: LICENSE
Requires-Dist: requests
Requires-Dist: tqdm
Requires-Dist: requests-toolbelt
Requires-Dist: pillow
Requires-Dist: locust (==1.1.0)
